code_separator/__init__.py
code_separator/cli.py
code_separator/core.py
code_separator/utils.py
auto_hash_separator-0.2.dist-info/METADATA
auto_hash_separator-0.2.dist-info/WHEEL
auto_hash_separator-0.2.dist-info/entry_points.txt
auto_hash_separator-0.2.dist-info/top_level.txt
auto_hash_separator-0.2.dist-info/RECORD
