Metadata-Version: 2.1
Name: auto_hash_separator
Version: 0.2
Summary: Python package for inserting hash separators between functions and classes.
Home-page: https://github.com/bantoinese83/Code_separator
Author: Bryan Antoine
Author-email: b.antoine.se@gmail.com
Classifier: Programming Language :: Python :: 3
Classifier: License :: OSI Approved :: MIT License
Classifier: Operating System :: OS Independent
Requires-Dist: halo
